Metadata-Version: 1.1
Name: numpyplus
Version: 0.1.14
Summary: An upgraded version of numpy
Home-page: https://github.com/Shashulovskiy/numpyplus
Author: Artem Shashulovskiy
Author-email: shashulovskiy@gmail.com
License: BSD 2-clause
Platform: UNKNOWN
Classifier: Development Status :: 1 - Planning
Classifier: Intended Audience :: Science/Research
Classifier: License :: OSI Approved :: BSD License
Classifier: Operating System :: POSIX :: Linux
Classifier: Programming Language :: Python :: 2
Classifier: Programming Language :: Python :: 2.7
Classifier: Programming Language :: Python :: 3
Classifier: Programming Language :: Python :: 3.4
Classifier: Programming Language :: Python :: 3.5
